docx2txt2/__init__.py
docx2txt2/py.typed
docx2txt2-1.0.4.dist-info/LICENSE.txt
docx2txt2-1.0.4.dist-info/METADATA
docx2txt2-1.0.4.dist-info/WHEEL
docx2txt2-1.0.4.dist-info/top_level.txt
docx2txt2-1.0.4.dist-info/RECORD
