Metadata-Version: 2.1
Name: docx2txt2
Version: 1.0.4
Summary: Extract text from .docx and .odt files to strings in pure python.
Author-email: Toby Devlin <toby@tobydevlin.com>
Maintainer-email: Toby Devlin <toby@tobydevlin.com>
License: MIT License
Project-URL: Repository, https://github.com/GitToby/docx2txt2.git
Project-URL: Bug Tracker, https://github.com/GitToby/docx2txt2/issues
Keywords: word,docx,odt,extract,text,images
Classifier: Development Status :: 5 - Production/Stable
Classifier: Intended Audience :: Developers
Classifier: License :: OSI Approved :: MIT License
Classifier: Programming Language :: Python
Classifier: Programming Language :: Python :: 3.8
Classifier: Programming Language :: Python :: 3.9
Classifier: Programming Language :: Python :: 3.10
Classifier: Programming Language :: Python :: 3.11
Classifier: Programming Language :: Python :: 3.12
Requires-Python: >=3.8
License-File: LICENSE.txt
Provides-Extra: dev
Requires-Dist: pytest >=8.1.1 ; extra == 'dev'
Requires-Dist: black >=24.2.0 ; extra == 'dev'
Requires-Dist: ruff >=0.3.2 ; extra == 'dev'
Requires-Dist: mypy >=1.9.0 ; extra == 'dev'
Requires-Dist: pytest-cov >=4.1.0 ; extra == 'dev'
Requires-Dist: pre-commit >=3.5.0 ; extra == 'dev'
Requires-Dist: docx2txt >=0.8 ; extra == 'dev'
Requires-Dist: pytest-benchmark >=4.0.0 ; extra == 'dev'
Requires-Dist: build >=1.1.1 ; extra == 'dev'
Requires-Dist: setuptools-scm >=8.0.4 ; extra == 'dev'
